explainit/__init__.py
explainit/app.py
explainit/banner.py
explainit/correlation.py
explainit/dashboard.py
explainit/header.py
explainit/py.typed
explainit/tabs.py
explainit/utils.py
explainit/workflow.py
explainit/analyzer/__init__.py
explainit/analyzer/data_summary.py
explainit/analyzer/feature_summary.py
explainit/assets/base-styles.css
explainit/assets/custom-styles.css
explainit/assets/explain-it-logo-trans.png
explainit/assets/fonts.css
explainit/assets/logo_white.png
explainit/assets/stat-tests-conditions.csv
explainit/correlations/__init__.py
explainit/correlations/correlation_heatmaps.py
explainit/correlations/correlation_table.py
explainit/correlations/correlations.py
explainit/graphs/__init__.py
explainit/graphs/additional_cat_graphs.py
explainit/graphs/additional_num_graphs.py
explainit/graphs/cat_target_plot.py
explainit/graphs/feature_stats_plots.py
explainit/graphs/num_target_plot.py
explainit/graphs/numerical_target_behaviour.py
explainit/stattests/__init__.py
explainit/stattests/chi2_test.py
explainit/stattests/jensenshannon_test.py
explainit/stattests/ks_test.py
explainit/stattests/stat_test.py
explainit/stattests/wasserstein_distance_test.py
explainit/stattests/z_test.py
explainit-1.2.1.dist-info/LICENSE
explainit-1.2.1.dist-info/METADATA
explainit-1.2.1.dist-info/WHEEL
explainit-1.2.1.dist-info/top_level.txt
explainit-1.2.1.dist-info/RECORD
