Metadata-Version: 2.1
Name: explainit
Version: 1.2.1
Summary: A modern, enterprise-ready business intelligence web application
Home-page: https://www.katonic.ai/
Author: Katonic Pty Ltd.
Author-email: shailesh.kumar@katonic.ai
License: Apache-2.0
Project-URL: Documentation, https://docs.katonic.ai/
Project-URL: Source, https://github.com/katonic-dev/explainit
Project-URL: Issues, https://github.com/katonic-dev/explainit/issues
Project-URL: Changelog, https://github.com/katonic-dev/explainit/blob/master/CHANGELOG.md
Platform: unix
Platform: linux
Platform: osx
Platform: cygwin
Platform: win32
Classifier: Programming Language :: Python :: 3.8
Classifier: Programming Language :: Python :: 3.9
Requires-Python: >=3.8
License-File: LICENSE
Requires-Dist: Brotli (>=1.0.9)
Requires-Dist: Flask (>=2.2.2)
Requires-Dist: Flask-Compress (>=1.12)
Requires-Dist: Jinja2 (<4,>3)
Requires-Dist: MarkupSafe (>=2.1.1)
Requires-Dist: Werkzeug (>=2.2.2)
Requires-Dist: certifi (>=2022.6.15)
Requires-Dist: click (<9.0.0,>8.0.0)
Requires-Dist: colorama
Requires-Dist: dash (>=2.6.1)
Requires-Dist: dash-core-components (>=2.0.0)
Requires-Dist: dash-daq (>=0.5.0)
Requires-Dist: dash-html-components (>=2.0.0)
Requires-Dist: dash-table (>=5.0.0)
Requires-Dist: importlib-metadata (==4.12.0)
Requires-Dist: itsdangerous (==2.1.2)
Requires-Dist: numpy (<3,>1.22)
Requires-Dist: orjson (>=3.7.12)
Requires-Dist: pandas (<2,>=1.4.3)
Requires-Dist: plotly (>=5.10.0)
Requires-Dist: python-dateutil (>=2.8.2)
Requires-Dist: pytz (>=2022.2.1)
Requires-Dist: six (>=1.16.0)
Requires-Dist: scipy (>=1.5.4)
Requires-Dist: tenacity (<9,>7)
Requires-Dist: zipp (==3.8.1)
Provides-Extra: testing
Requires-Dist: flake8 (>=3.9) ; extra == 'testing'
Requires-Dist: mypy (>=0.910) ; extra == 'testing'
Requires-Dist: pytest (>=6.0) ; extra == 'testing'
Requires-Dist: pytest-cov (>=2.0) ; extra == 'testing'
Requires-Dist: tox (==3.14.6) ; extra == 'testing'
Requires-Dist: virtualenv (==20.0.33) ; extra == 'testing'
